faust_s3_backed_serializer/__init__.py
faust_s3_backed_serializer/s3_serializer.py
faust_s3_backed_serializer-1.1.0.dist-info/LICENSE
faust_s3_backed_serializer-1.1.0.dist-info/WHEEL
faust_s3_backed_serializer-1.1.0.dist-info/METADATA
faust_s3_backed_serializer-1.1.0.dist-info/RECORD
