Metadata-Version: 2.1
Name: faust-s3-backed-serializer
Version: 1.1.0
Summary: Faust serializer that serializes large messages on Amazon S3
Home-page: https://github.com/bakdata/faust-s3-backed-serializer
Author: bakdata
Author-email: opensource@bakdata.com
Requires-Python: >=3.6
Classifier: Programming Language :: Python :: 3
Classifier: Programming Language :: Python
Classifier: Topic :: Internet
Classifier: Topic :: Software Development :: Libraries :: Application Frameworks
Classifier: Topic :: Software Development :: Libraries :: Python Modules
Classifier: Topic :: Software Development :: Libraries
Classifier: Topic :: Software Development
Classifier: Typing :: Typed
Classifier: Intended Audience :: Developers
Classifier: License :: OSI Approved :: MIT License
Classifier: Programming Language :: Python :: 3 :: Only
Classifier: Programming Language :: Python :: 3.6
Classifier: Programming Language :: Python :: 3.7
Classifier: Programming Language :: Python :: 3.8
Requires-Dist: boto3
Requires-Dist: faust-streaming
Requires-Dist: bump2version
Requires-Dist: pytest ; extra == "test"
Requires-Dist: pytest-cov ; extra == "test"
Requires-Dist: botocore ; extra == "test"
Provides-Extra: test
